{
  "config": {
    "step": {
      "user": {
        "title": "Smartmeter",
        "description": "The smart meter must be connected via a M-BUS to USB converter, please select serial port of your USB device.",
        "data": {
          "supplier": "Supplier",
          "com_port": "USB port",
          "key_hex": "Key"
        }
      }
    },
    "error": {
      "cannot_connect": "Unable to connect, please check serial port and electrical connection",
      "invalid_serial_port": "Serial port is not a valid device or could not be opened",
      "cannot_open_serial_port": "Cannot open serial port, please check and try again"
    },
    "abort": {
      "already_configured": "[%key:common::config_flow::abort::already_configured_device%]",
      "no_serial_ports": "No com ports found. Need a valid M-BUS to USB device to communicate."
    }
  }
}